ismember/__init__.py
ismember/example.py
ismember/ismember.py
ismember-1.1.0.dist-info/licenses/LICENSE
ismember-1.1.0.dist-info/METADATA
ismember-1.1.0.dist-info/WHEEL
ismember-1.1.0.dist-info/top_level.txt
ismember-1.1.0.dist-info/RECORD
