Metadata-Version: 2.4
Name: ismember
Version: 1.1.0
Summary: Python package ismember returns array elements that are members of set array.
Author-email: Erdogan Taskesen <erdogant@gmail.com>
License: MIT License
Project-URL: Homepage, https://erdogant.github.io/ismember
Project-URL: Download, https://github.com/erdogant/ismember/archive/{version}.tar.gz
Keywords: Python,
Classifier: Programming Language :: Python :: 3
Classifier: License :: OSI Approved :: MIT License
Classifier: Operating System :: OS Independent
Requires-Python: >=3
License-File: LICENSE
Requires-Dist: numpy
Dynamic: license-file
